{
  "numero_requisicao": "",
  "document_number": "UP",
  "po_number": "UP",
  "supplier_name": "",
  "delivery_date": "02-10-2025",
  "qr_codes": [],
  "produtos": [
    {
      "referencia_ordem": "",
      "artigo": "E0748001901",
      "descricao": "BALTIC fb, TOFFEE 5159-250602064",
      "lote_producao": "",
      "quantidade": 34.0,
      "unidade": "ML",
      "volume": 0,
      "dimensoes": "",
      "peso": 0.0,
      "iva": 23.0,
      "total": 0.0
    },
    {
      "referencia_ordem": "",
      "artigo": "E0624085501",
      "descricao": "OPERA fb, PEARL 5144-2320",
      "lote_producao": "",
      "quantidade": 4850.0,
      "unidade": "ML",
      "volume": 0,
      "dimensoes": "",
      "peso": 0.0,
      "iva": 23.0,
      "total": 0.0
    },
    {
      "referencia_ordem": "",
      "artigo": "EO05S9024501",
      "descricao": "PRINCE fb, ASH 5183-620154H",
      "lote_producao": "",
      "quantidade": 104.0,
      "unidade": "ML",
      "volume": 0,
      "dimensoes": "",
      "peso": 0.0,
      "iva": 23.0,
      "total": 0.0
    },
    {
      "referencia_ordem": "",
      "artigo": "E0173015701",
      "descricao": "SAVANA fb, FOREST 5041-313040",
      "lote_producao": "",
      "quantidade": 105.0,
      "unidade": "ML",
      "volume": 0,
      "dimensoes": "",
      "peso": 0.0,
      "iva": 23.0,
      "total": 0.0
    },
    {
      "referencia_ordem": "",
      "artigo": "E0173016901",
      "descricao": "SAVANA fb, DARK GREY JL 5153-725018t",
      "lote_producao": "",
      "quantidade": 47.0,
      "unidade": "ML",
      "volume": 0,
      "dimensoes": "",
      "peso": 0.0,
      "iva": 23.0,
      "total": 0.0
    },
    {
      "referencia_ordem": "",
      "artigo": "E0748022501",
      "descricao": "BALTIC fb, BLACK 5083-250507059",
      "lote_producao": "",
      "quantidade": 3250.0,
      "unidade": "ML",
      "volume": 0,
      "dimensoes": "",
      "peso": 0.0,
      "iva": 23.0,
      "total": 0.0
    },
    {
      "referencia_ordem": "",
      "artigo": "E0624003001",
      "descricao": "OPERA fb, STONE 5091-3501",
      "lote_producao": "",
      "quantidade": 4440.0,
      "unidade": "ML",
      "volume": 0,
      "dimensoes": "",
      "peso": 0.0,
      "iva": 23.0,
      "total": 0.0
    },
    {
      "referencia_ordem": "",
      "artigo": "E0748031401",
      "descricao": "BALTIC fbo, CEMENT 5083-250405007",
      "lote_producao": "",
      "quantidade": 4200.0,
      "unidade": "ML",
      "volume": 0,
      "dimensoes": "",
      "peso": 0.0,
      "iva": 23.0,
      "total": 0.0
    },
    {
      "referencia_ordem": "",
      "artigo": "E0624003001",
      "descricao": "OPERA fb, STONE 5116-2919H1-1",
      "lote_producao": "",
      "quantidade": 41.0,
      "unidade": "ML",
      "volume": 0,
      "dimensoes": "",
      "peso": 0.0,
      "iva": 23.0,
      "total": 0.0
    },
    {
      "referencia_ordem": "",
      "artigo": "E0624003001",
      "descricao": "OPERA fb, STONE 5144-2624-3",
      "lote_producao": "",
      "quantidade": 4180.0,
      "unidade": "ML",
      "volume": 0,
      "dimensoes": "",
      "peso": 0.0,
      "iva": 23.0,
      "total": 0.0
    },
    {
      "referencia_ordem": "",
      "artigo": "Garantimos",
      "descricao": "artigos STANDARD",
      "lote_producao": "",
      "quantidade": 100.0,
      "unidade": "BY",
      "volume": 0,
      "dimensoes": "",
      "peso": 0.0,
      "iva": 23.0,
      "total": 0.0
    }
  ],
  "lines": [],
  "totals": {
    "total_lines": 11,
    "total_quantity": 21351.0
  },
  "tipo_documento": "FATURA_ELASTRON",
  "texto_completo": "--- Página 1 ---\nO0OO ELASTRONGROUP.COM\n\nDDD ATCUD: JJATK5S6R-5595\nElastron Portugal, SA GROUFP\nRua da Recta de Gomil, nº 354 - Armazém A2 Página 1/2\n4595-144 Frazão\nPaços de Ferreira - Portugal\nTelefone.: +351 227 624 043* Exmo.(s) Senhor(s), Entregue a\nNIF.: PT 500 772 894 Colmol- Colchões S.A Colmoal- Colchões S.A\ngeral&Qelastrongroup.com Zona Industrial das Cavadas Zona Industrial das Cavadas\nCapital Social 2 500 000,00 EUR\nCons. Reg. Com. Gaia Vila de Cucujaes Vila de Cucujaes\nMatricula N.º 500772894 3720-760 Vila de Cucujaes 3720-760 Vila de Cucujaes\nOriginal\nFatura 25EU/5595 (1FWH)\nNIF No. Cliente Doc. No Moeda Camblo Data\nPT 500248800 5219 4210 EUR 1,0000 02-10-2025\nDesconto Cliente Desc. Fin. Data Vencimento Termo Pagamento Condições Entrega Modo de Envio\n\n0,00 0,00 31/12/2025 60 dias final de mes DAP - Vila de Cucujaes Ni Viatura - Rota3 Sul\nArtigo Descrição Lote Quant.  Un. Vol. Preço Desconto a Toftal\nProdução Un.\n1ECWH Nº 10874/25EU de 04-09-2025\nE0748001901 BALTIC fb, TOFFEE 5159-250602064 34,00 ML 1 3,99 300 23,00 131,59\n1ECWH Nº 10954/25EU de 05-09-2025\n\nE0942104801 VIVALD! fo, TRUFFLE 5037-250623 ML 1\n\n1ECWH Nº 10955/25EU de 05-09-2025\nE0624085501 OPERA fb, PEARL 5144-2320 4850 ML 1 2,49 19688 23,00 97,00\n\n1ECWH Nº 10966/25EU de 05-09-2025\nE0748031401 BALTIC fbo, CEMENT 5159-250522072\n\n1ECWH Nº 11108/25EU de 09-09-2025\nEO05S9024501 PRINCE fb, ASH 5183-620154H 104,00 ML 2 1,98 1414  23,00 176,80\n\n1ECWH Nº 11754/25EU de 22-09-2025\nE0173015701 SAVANA fb, FOREST 5041-313040 105,00 ML 2 1,98 1414  23,00 178,50\n\n1ECWH Nº 11877/25EU de 24-09-2025\n\nE0173016901 SAVANA fb, DARK GREY JL 5153-725018t 47,00 ML 1 1,98 1414  23,00 79,90\nE0748022501 BALTIC fb, BLACK 5083-250507059 3250 ML 1 3,99 300 2300 125,79\nE0624003001 OPERA fb, STONE 5091-3501 4440 ML 1 2,49 19688 23,00 88,80\n\n1ECWH Nº 11970/25EU de 25-09-2025\nE0748031401 BALTIC fbo, CEMENT 5083-250405007\n\n1ECWH Nº 12028/25EU de 26-09-2025\nE0748031401 BALTIC fbo, CEMENT 5083-250405007 4200 ML 1 3,99 300 2300 162,55\n\nE0624003001 OPERA fb, STONE 5116-2919H1-1 41,00 ML 1 2,49 19688 23,00 82,00\n\n1ECWH Nº 12119/25EU de 29-09-2025\nE0624003001 OPERA fb, STONE 5144-2624-3 4180 ML 1 2,49 19688 23,00 82,60\n\n1GRWH 25ELU/N.º5589 de 02/10/2025 07:34\ndeco31\ndeco3o\ndeco13\ndeco3o\ndeco13\n\ndeco1\n\ndeco25\ndeco24\n2(savdarkgrey)\ndeco32\ndeco10\ndeco22\ndeco22\ndeco10\ndeco10\n\nELASDVO2\n\n\n--- Página 2 ---\nElastron Portugal, SA\nRua da Recta de Gomil, nº 354 - Armazém A2\n\nA4695-144 Frazão\nPaços de Ferreira - Portugal\nTelefone.: +351 227 624 043 *\nNIF.: PT 500 772 894\ngeral&elastrongroup.com\nCapital Social 2500 000,00 EUR\nCons. Reg. Com. Gaia\n\nMatricula N.º 500772894\n\nO000\n\nEC—\n\nO000\nelastron\n\n6G ROUFP\n\nExmo.(s) Senhor(s),\nGolmol- Colchões S.A\nZona Industrial das Cavadas\n\nVila de Cucujaes\n3720-760 Vila de Cucujaes\n\nELASTRONGROUP.COM\n\nPágina 2/2\n\nEntregue a\nColmoal- Colchões S.A\n\nZona Industrial das Cavadas\n\nVila de Cucujaes\n3720-760 Vila de Cucujaes\n\nOriginal\nFatura 25EU/5595 (1FWH)\nNIF No. Cliente Doc. No Moeda Camblo Data\nPT 500248800 5219 4210 EUR 1,0000 02-10-2025\nDesconto Cliente Desc. Fin. Data Vencimento Termo Pagamento Condições Entrega Modo de Envio\n0,00 0,00 31/12/2025 60 dias final de mes DAP - Vila de Cucujaes Ni Viatura - Rota3 Sul\nArtigo Descrição Lote Quant.  Un. Vol. Preço Desconto a Toftal\nProdução Un.\nTotal de Metros: 637,80 / Nº de Volumes: 15— Peso Liquido: 250,25 kg\nGarantimos artigos STANDARD 100 by OEKO-TEXQ anexo 4 classe || apenas quando soticitado por escrito pelo cliente.Os Produtos são propriedade\nexclusiva do vendedor atê o pagamento integral do valor de compra.\neGjá-Processado por Programa Certificado n.º 0030/AT / FT 1FWH.25EU/5595 | Os bens e/ou serviços foram colocados à disposição na data 2025-10-02/Q Ce\n* Chamada para a rede fixa nacional.Produtor Emb: PTO1111114.\nAo receber este documento, o cliente declara que leu os Termos e Condições Gerais de Venda e as informações técnicas detalhadas sobre os produtos,\ndisponíveis no site www.elastrongroup.com.\nATCUD: JJATK56R-5595 Total Mercadoria 1 829.08\nTaxa Base Incidôncia Total lva Motivo Isenção Desc. Cliente Com. Total -187.81\n23,00 1641,27 377,49 Desc. Cliente Fin. Total 0.,00\nCusto Transnorte 0.00\nOutros Serv. 0.00\nTotal Adiantamento 9.00\nIva 377,49\nCarga Dascarga\nNf Morada - 2025-10-02 / 08:12 Vi Morada Tofal (EUR ) 2018.76\n\nRua da Recta de Gomil\nFrazão\n\n4595-144 Frazão\nPortuga! (Porto)\n\nSTANDARD Iªâªí\n| 100\n\nZona Industrial das Cavadas\nVila de Cucujaes\n\n3720-760 Vila de Cucujaes\nPortuga! (Aveiro)\n\nTE-00025098\n\nBanco: SANTANDER TOTTA\n\nIBAN: PT50 0018 0000 0035 7622 0016 8\nSWIFT: TOTAPTPL\n\nBanco: BPI\n\nIBAN: PT50 0010 0000 5543 8990 0018 9\nSWIFT: BBPIPTPL\n\nElastron Portugal SA is a GRS/RCS certified company.\n\nGlobal Recycled\nw Standard\n\nOnly products wich are covered by a valid Transaction\nCertificate are GRS/RCS certífied.\n\nELASDVO2",
  "baixa_qualidade_texto": false,
  "strategy_used": "Tesseract com Preprocessing (DPI 200)"
}